logo_qrcode/__init__.py
logo_qrcode/logo_qrcode.py
logo_qrcode-0.0.4.dist-info/METADATA
logo_qrcode-0.0.4.dist-info/WHEEL
logo_qrcode-0.0.4.dist-info/entry_points.txt
logo_qrcode-0.0.4.dist-info/RECORD
