Metadata-Version: 2.1
Name: logo-qrcode
Version: 0.0.4
Summary: A simple library for generating QR codes with logo
Project-URL: Bug Tracker, https://github.com/hellofan1998/logo_qrcode/issues
Project-URL: Homepage, https://github.com/hellofan1998/logo_qrcode
Author-email: Fan <fan@example.com>
Classifier: License :: OSI Approved :: MIT License
Classifier: Operating System :: OS Independent
Classifier: Programming Language :: Python :: 3
Requires-Python: >=3.8
Requires-Dist: pillow
Requires-Dist: qrcode
